tsukkomi/__init__.py
tsukkomi/typed.py
tsukkomi-0.0.6.dist-info/DESCRIPTION.rst
tsukkomi-0.0.6.dist-info/METADATA
tsukkomi-0.0.6.dist-info/metadata.json
tsukkomi-0.0.6.dist-info/RECORD
tsukkomi-0.0.6.dist-info/top_level.txt
tsukkomi-0.0.6.dist-info/WHEEL
