Metadata-Version: 2.0
Name: tsukkomi
Version: 0.0.6
Summary: make tsukkomi for python types
Home-page: https://github.com/spoqa/tsukkomi
Author: Kang Hyojun
Author-email: ed@spoqa.com
License: Public Domain
Platform: UNKNOWN
Classifier: Development Status :: 3 - Alpha
Classifier: Intended Audience :: Developers
Classifier: License :: OSI Approved :: Apache Software License
Classifier: Operating System :: OS Independent
Classifier: Programming Language :: Python :: 3
Classifier: Programming Language :: Python :: 3.3
Classifier: Programming Language :: Python :: 3.4
Classifier: Programming Language :: Python :: 3.5
Classifier: Programming Language :: Python :: 3 :: Only
Classifier: Programming Language :: Python :: Implementation :: CPython
Classifier: Topic :: Software Development :: Libraries :: Python Modules
Requires-Dist: setuptools
Requires-Dist: typing; python_version<'3.5'
Provides-Extra: docs
Requires-Dist: Sphinx; extra == 'docs'
Provides-Extra: tests
Requires-Dist: pytest (>=2.9.0); extra == 'tests'
Requires-Dist: import-order; extra == 'tests'
Requires-Dist: flake8; extra == 'tests'
